gsd-4.2.0.dist-info/RECORD
gsd-4.2.0.dist-info/WHEEL
gsd-4.2.0.dist-info/entry_points.txt
gsd-4.2.0.dist-info/top_level.txt
gsd-4.2.0.dist-info/METADATA
gsd-4.2.0.dist-info/licenses/LICENSE
gsd/pytest_plugin_validate.py
gsd/gsd.h
gsd/fl.c
gsd/conftest.py
gsd/version.py
gsd/hoomd.py
gsd/__init__.py
gsd/libgsd.pxd
gsd/fl.pyx
gsd/gsd.c
gsd/pygsd.py
gsd/__main__.py
gsd/fl.abi3.so
gsd/test/conftest.py
gsd/test/pytest.ini
gsd/test/test_gsd_v1.gsd
gsd/test/test_fl.py
gsd/test/test_largefile.py
gsd/test/test_hoomd.py
