Metadata-Version: 2.4
Name: gsd
Version: 4.2.0
Summary: General simulation data file format.
Author-email: "Joshua A. Anderson" <joaander@umich.edu>
License-Expression: BSD-2-Clause
Project-URL: Homepage, https://gsd.readthedocs.io
Project-URL: Documentation, https://gsd.readthedocs.io
Project-URL: Source, https://github.com/glotzerlab/gsd
Project-URL: Issues, https://github.com/glotzerlab/gsd/issues
Classifier: Development Status :: 5 - Production/Stable
Classifier: Intended Audience :: Developers
Classifier: Intended Audience :: Science/Research
Classifier: Operating System :: MacOS :: MacOS X
Classifier: Operating System :: POSIX
Classifier: Topic :: Scientific/Engineering :: Physics
Requires-Python: >=3.11
License-File: LICENSE
Requires-Dist: numpy
Dynamic: license-file
